DeltaCenter/__init__.py
DeltaCenter/__main__.py
DeltaCenter/client.py
DeltaCenter/config.yml
DeltaCenter/cookie.py
DeltaCenter/utils.py
delta_center_client-0.0.4.dist-info/METADATA
delta_center_client-0.0.4.dist-info/WHEEL
delta_center_client-0.0.4.dist-info/top_level.txt
delta_center_client-0.0.4.dist-info/RECORD
