Metadata-Version: 2.1
Name: delta-center-client
Version: 0.0.4
Summary: The client for delta center (used with opendelta).
Requires-Dist: oss2 (==2.15.0)
Requires-Dist: yacs (>=0.1.6)
